pyupgw/__init__.py
pyupgw/__main__.py
pyupgw/_api.py
pyupgw/_mqtt.py
pyupgw/client.py
pyupgw/errors.py
pyupgw/models.py
pyupgw/cli/__init__.py
pyupgw/cli/_logging.py
pyupgw/cli/commands.py
pyupgw/cli/tui.py
pyupgw-0.13.dist-info/entry_points.txt
pyupgw-0.13.dist-info/LICENSE
pyupgw-0.13.dist-info/WHEEL
pyupgw-0.13.dist-info/METADATA
pyupgw-0.13.dist-info/RECORD
