Metadata-Version: 2.1
Name: pyupgw
Version: 0.13
Summary: Python client for Unisenza Plus
Author-email: Jaakko Moisio <jaakko@moisio.fi>
Requires-Python: >=3.11
Classifier: License :: OSI Approved :: MIT License
Classifier: Programming Language :: Python :: 3
Classifier: Programming Language :: Python :: 3 :: Only
Classifier: Programming Language :: Python :: 3.11
Classifier: Programming Language :: Python :: 3.12
Classifier: Programming Language :: Python :: 3.13
Classifier: Intended Audience :: Developers
Classifier: Topic :: Internet
Classifier: Topic :: Home Automation
Classifier: Topic :: Software Development :: Libraries
Classifier: Topic :: Software Development :: Libraries :: Python Modules
Requires-Dist: pycognito
Requires-Dist: awscrt
Requires-Dist: attrs
Requires-Dist: dict-deep
Requires-Dist: aiohttp
Requires-Dist: paho-mqtt>=2,<3
Requires-Dist: python-dotenv ; extra == "cli"
Requires-Dist: click ; extra == "cli"
Requires-Dist: rich ; extra == "cli"
Requires-Dist: rich-click ; extra == "cli"
Requires-Dist: blessed ; extra == "cli"
Requires-Dist: jsonformatter ; extra == "cli"
Requires-Dist: PyYAML ; extra == "cli"
Requires-Dist: ruff>=0.2.2 ; extra == "dev"
Requires-Dist: mypy>=1.7 ; extra == "dev"
Requires-Dist: pytest>=7.4.3,<8 ; extra == "dev"
Requires-Dist: pytest-asyncio>=0.23.2 ; extra == "dev"
Requires-Dist: hypothesis>=6.92.1 ; extra == "dev"
Requires-Dist: tox>=4.11.4 ; extra == "dev"
Requires-Dist: coverage>=7.4 ; extra == "dev"
Requires-Dist: types-PyYAML ; extra == "dev"
Requires-Dist: sphinx>=7.2.6 ; extra == "doc"
Requires-Dist: sphinx-rtd-theme ; extra == "doc"
Project-URL: Documentation, https://pyupgw.readthedocs.io/
Project-URL: Source, https://github.com/jasujm/pyupgw
Provides-Extra: cli
Provides-Extra: dev
Provides-Extra: doc
